Metadata-Version: 1.0
Name: linear-model-extension
Version: 0.1
Summary: Linear Model Extension
Home-page: UNKNOWN
Author: UNKNOWN
Author-email: UNKNOWN
License: UNKNOWN
Platform: UNKNOWN
